{"duration":76.8,"wordTimings":[{"word":"Ever","start":0,"end":0.221},{"word":"wonder","start":0.267,"end":0.511},{"word":"how","start":0.557,"end":0.673},{"word":"this","start":0.731,"end":0.871},{"word":"looks","start":0.929,"end":1.138},{"word":"in","start":1.184,"end":1.242},{"word":"my","start":1.289,"end":1.382},{"word":"day-to-day?","start":1.44,"end":2.171},{"word":"Mornings?","start":2.577,"end":3.309},{"word":"Oh,","start":3.657,"end":4.005},{"word":"that's","start":4.052,"end":4.261},{"word":"when","start":4.284,"end":4.389},{"word":"I","start":4.423,"end":4.447},{"word":"go","start":4.516,"end":4.598},{"word":"into","start":4.656,"end":4.807},{"word":"Scatter","start":4.865,"end":5.178},{"word":"Mode.","start":5.201,"end":5.631},{"word":"I","start":5.851,"end":5.909},{"word":"dive","start":6.014,"end":6.269},{"word":"into","start":6.304,"end":6.455},{"word":"all","start":6.513,"end":6.629},{"word":"sorts","start":6.687,"end":6.908},{"word":"of","start":6.943,"end":7.001},{"word":"exploratory,","start":7.047,"end":7.721},{"word":"generative","start":7.779,"end":8.243},{"word":"work.","start":8.278,"end":8.707},{"word":"It's","start":8.998,"end":9.16},{"word":"like","start":9.195,"end":9.323},{"word":"a","start":9.346,"end":9.369},{"word":"buffet","start":9.427,"end":9.706},{"word":"of","start":9.752,"end":9.799},{"word":"research","start":9.857,"end":10.228},{"word":"topics!","start":10.275,"end":10.971},{"word":"I","start":11.517,"end":11.564},{"word":"also","start":11.645,"end":11.865},{"word":"kick","start":11.923,"end":12.086},{"word":"off","start":12.132,"end":12.237},{"word":"some","start":12.272,"end":12.411},{"word":"AI","start":12.457,"end":12.69},{"word":"tasks","start":12.748,"end":13.096},{"word":"in","start":13.142,"end":13.212},{"word":"parallel","start":13.27,"end":13.676},{"word":"—","start":13.839,"end":13.885},{"word":"think","start":14.071,"end":14.303},{"word":"image","start":14.361,"end":14.605},{"word":"generation,","start":14.64,"end":15.22},{"word":"writing","start":15.278,"end":15.615},{"word":"drafts,","start":15.65,"end":16.091},{"word":"and","start":16.114,"end":16.23},{"word":"even","start":16.288,"end":16.451},{"word":"coding","start":16.509,"end":16.857},{"word":"a","start":16.915,"end":16.939},{"word":"bit.","start":16.973,"end":17.345},{"word":"Honestly,","start":17.809,"end":18.378},{"word":"it","start":18.436,"end":18.564},{"word":"feels","start":18.61,"end":18.819},{"word":"a","start":18.854,"end":18.877},{"word":"bit","start":18.912,"end":19.04},{"word":"like","start":19.086,"end":19.237},{"word":"being","start":19.272,"end":19.446},{"word":"a","start":19.481,"end":19.504},{"word":"conductor,","start":19.551,"end":20.143},{"word":"juggling","start":20.329,"end":20.689},{"word":"multiple","start":20.735,"end":21.107},{"word":"streams","start":21.13,"end":21.432},{"word":"of","start":21.467,"end":21.525},{"word":"creativity","start":21.583,"end":22.21},{"word":"without","start":22.43,"end":22.744},{"word":"really","start":22.802,"end":22.999},{"word":"diving","start":23.057,"end":23.347},{"word":"deep","start":23.394,"end":23.591},{"word":"into","start":23.649,"end":23.823},{"word":"any","start":23.905,"end":24.09},{"word":"single","start":24.16,"end":24.462},{"word":"one.","start":24.508,"end":24.915},{"word":"Fun,","start":25.658,"end":26.087},{"word":"right?","start":26.227,"end":26.703},{"word":"Afternoons?","start":27.109,"end":27.91},{"word":"That’s","start":28.456,"end":28.7},{"word":"when","start":28.723,"end":28.839},{"word":"I","start":28.886,"end":28.909},{"word":"go","start":28.979,"end":29.071},{"word":"into","start":29.129,"end":29.304},{"word":"Laser","start":29.362,"end":29.605},{"word":"Mode.","start":29.64,"end":30.035},{"word":"I","start":30.383,"end":30.418},{"word":"mean,","start":30.476,"end":30.778},{"word":"it's","start":30.917,"end":31.08},{"word":"like","start":31.115,"end":31.231},{"word":"a","start":31.254,"end":31.277},{"word":"switch","start":31.324,"end":31.556},{"word":"flips.","start":31.579,"end":32.09},{"word":"I","start":32.253,"end":32.311},{"word":"shut","start":32.392,"end":32.578},{"word":"down","start":32.624,"end":32.787},{"word":"all","start":32.833,"end":32.938},{"word":"those","start":32.984,"end":33.147},{"word":"parallel","start":33.193,"end":33.541},{"word":"streams...","start":33.599,"end":34.203},{"word":"focus","start":34.609,"end":34.888},{"word":"on","start":34.946,"end":35.004},{"word":"one","start":35.062,"end":35.19},{"word":"problem,","start":35.225,"end":35.712},{"word":"one","start":35.875,"end":36.049},{"word":"screen.","start":36.084,"end":36.571},{"word":"Sometimes","start":37.21,"end":37.674},{"word":"I’m","start":37.709,"end":37.814},{"word":"chatting","start":37.86,"end":38.174},{"word":"with","start":38.197,"end":38.301},{"word":"an","start":38.336,"end":38.394},{"word":"AI,","start":38.441,"end":38.812},{"word":"but","start":38.859,"end":39.033},{"word":"most","start":39.149,"end":39.358},{"word":"of","start":39.404,"end":39.451},{"word":"the","start":39.486,"end":39.555},{"word":"time","start":39.59,"end":39.822},{"word":"it’s","start":39.88,"end":40.031},{"word":"just","start":40.078,"end":40.252},{"word":"me","start":40.31,"end":40.414},{"word":"and","start":40.449,"end":40.519},{"word":"the","start":40.542,"end":40.612},{"word":"code.","start":40.647,"end":41.088},{"word":"This","start":41.378,"end":41.564},{"word":"is","start":41.611,"end":41.68},{"word":"where","start":41.715,"end":41.854},{"word":"the","start":41.889,"end":41.959},{"word":"tough","start":42.005,"end":42.179},{"word":"decisions","start":42.226,"end":42.597},{"word":"come","start":42.644,"end":42.783},{"word":"into","start":42.806,"end":42.946},{"word":"play.","start":43.004,"end":43.433},{"word":"Now,","start":43.898,"end":44.211},{"word":"let","start":44.269,"end":44.409},{"word":"me","start":44.443,"end":44.525},{"word":"tell","start":44.559,"end":44.722},{"word":"you,","start":44.78,"end":45.012},{"word":"the","start":45.175,"end":45.291},{"word":"transition","start":45.337,"end":45.779},{"word":"ritual","start":45.825,"end":46.092},{"word":"is","start":46.15,"end":46.22},{"word":"key.","start":46.278,"end":46.684},{"word":"You","start":47.09,"end":47.207},{"word":"can't","start":47.253,"end":47.439},{"word":"just","start":47.474,"end":47.601},{"word":"go","start":47.636,"end":47.729},{"word":"from","start":47.787,"end":47.915},{"word":"Scatter","start":47.973,"end":48.275},{"word":"to","start":48.31,"end":48.368},{"word":"Laser","start":48.426,"end":48.716},{"word":"in","start":48.797,"end":48.913},{"word":"a","start":48.948,"end":48.971},{"word":"snap.","start":49.041,"end":49.563},{"word":"I","start":50.109,"end":50.167},{"word":"close","start":50.272,"end":50.515},{"word":"tabs,","start":50.55,"end":51.073},{"word":"pause","start":51.212,"end":51.467},{"word":"any","start":51.491,"end":51.618},{"word":"background","start":51.665,"end":52.036},{"word":"stuff,","start":52.083,"end":52.547},{"word":"and","start":52.71,"end":52.849},{"word":"take","start":52.895,"end":53.07},{"word":"about","start":53.104,"end":53.29},{"word":"five","start":53.348,"end":53.569},{"word":"minutes","start":53.604,"end":53.836},{"word":"to","start":53.859,"end":53.917},{"word":"really","start":53.975,"end":54.173},{"word":"shift","start":54.219,"end":54.463},{"word":"gears.","start":54.521,"end":55.067},{"word":"Trust","start":55.473,"end":55.74},{"word":"me,","start":55.786,"end":56.042},{"word":"jumping","start":56.262,"end":56.576},{"word":"straight","start":56.622,"end":56.843},{"word":"into","start":56.866,"end":56.994},{"word":"Laser","start":57.052,"end":57.272},{"word":"Mode","start":57.319,"end":57.528},{"word":"is","start":57.586,"end":57.725},{"word":"a","start":57.772,"end":57.806},{"word":"one-way","start":57.911,"end":58.282},{"word":"ticket","start":58.341,"end":58.619},{"word":"to","start":58.666,"end":58.735},{"word":"making","start":58.793,"end":59.049},{"word":"mistakes!","start":59.084,"end":59.78},{"word":"Here’s","start":60.245,"end":60.465},{"word":"my","start":60.512,"end":60.581},{"word":"go-to","start":60.639,"end":60.906},{"word":"guideline:","start":60.964,"end":61.556},{"word":"if","start":61.963,"end":62.079},{"word":"the","start":62.125,"end":62.195},{"word":"task","start":62.241,"end":62.485},{"word":"has","start":62.52,"end":62.636},{"word":"dependencies","start":62.683,"end":63.321},{"word":"or","start":63.484,"end":63.623},{"word":"you","start":63.681,"end":63.762},{"word":"really","start":63.867,"end":64.146},{"word":"need","start":64.18,"end":64.331},{"word":"to","start":64.354,"end":64.413},{"word":"weigh","start":64.459,"end":64.622},{"word":"some","start":64.656,"end":64.796},{"word":"competing","start":64.831,"end":65.248},{"word":"tradeoffs...","start":65.283,"end":66.026},{"word":"it’s","start":66.375,"end":66.537},{"word":"definitely","start":66.572,"end":67.002},{"word":"a","start":67.071,"end":67.118},{"word":"Laser","start":67.199,"end":67.466},{"word":"situation.","start":67.501,"end":68.198},{"word":"But","start":68.604,"end":68.743},{"word":"if","start":68.766,"end":68.824},{"word":"it’s","start":68.871,"end":68.999},{"word":"more","start":69.045,"end":69.208},{"word":"about","start":69.242,"end":69.417},{"word":"exploring","start":69.451,"end":69.858},{"word":"ideas,","start":69.916,"end":70.531},{"word":"generating","start":70.636,"end":71.1},{"word":"new","start":71.158,"end":71.286},{"word":"stuff,","start":71.344,"end":71.855},{"word":"or","start":72.04,"end":72.157},{"word":"the","start":72.215,"end":72.284},{"word":"subtasks","start":72.331,"end":72.888},{"word":"can","start":72.946,"end":73.062},{"word":"stand","start":73.12,"end":73.329},{"word":"on","start":73.376,"end":73.434},{"word":"their","start":73.468,"end":73.608},{"word":"own","start":73.666,"end":73.852},{"word":"—","start":74.014,"end":74.095},{"word":"then","start":74.153,"end":74.339},{"word":"you","start":74.397,"end":74.49},{"word":"want","start":74.548,"end":74.722},{"word":"to","start":74.769,"end":74.85},{"word":"Scatter.","start":74.92,"end":75.465},{"word":"Simple","start":75.628,"end":75.907},{"word":"enough,","start":75.93,"end":76.174},{"word":"right?","start":76.208,"end":76.766}]}